framers/__init__.py
framers-0.1.0.dist-info/METADATA
framers-0.1.0.dist-info/WHEEL
framers-0.1.0.dist-info/RECORD
